Metadata-Version: 1.2
Name: fab-auth-keycloak2
Version: 0.1.2
Summary: Flask AppBuilder Authentication plugin
Home-page: https://github.com/hyunjong-lee/fab-auth-keycloak
Author: Hyunjong Lee
Author-email: hyunjong.lee.s@gmail.com
License: LGPLv2+
Download-URL: https://github.com/hyunjong-lee/fab-auth-keycloak/archive/v0.1.2.tar.gz
Project-URL: Source, https://github.com/hyunjong-lee/fab-auth-keycloak
Keywords: keycloak,AzureAD,superset
Platform: UNKNOWN
Classifier: Development Status :: 3 - Alpha
Classifier: Intended Audience :: Developers
Classifier: License :: OSI Approved :: GNU Lesser General Public License v2 or later (LGPLv2+)
Classifier: Programming Language :: Python :: 3.6
Classifier: Programming Language :: Python :: 3.7
Classifier: Programming Language :: Python :: 3.8
Requires-Python: >=3.6
